kpbill/__init__.py
kpbill/core/__init__.py
kpbill/core/calculator.py
kpbill/core/data_models.py
kpbill/core/policy_parser.py
kpbill/core/usage_parser.py
kpbill/data/20241024.json
kpbill/data/timeline.json
kpbill/exceptions.py
kpbill-0.1.241024.dist-info/METADATA
kpbill-0.1.241024.dist-info/WHEEL
kpbill-0.1.241024.dist-info/RECORD
