Metadata-Version: 2.1
Name: kpbill
Version: 0.1.241024
Summary: 전기요금 계산 라이브러리
Author: Wibaek Park
Author-email: wibaek@ninewatt.com
Requires-Python: >=3.9,<4.0
Classifier: Programming Language :: Python :: 3
Classifier: Programming Language :: Python :: 3.9
Classifier: Programming Language :: Python :: 3.10
Classifier: Programming Language :: Python :: 3.11
Classifier: Programming Language :: Python :: 3.12
Classifier: Programming Language :: Python :: 3.13
Requires-Dist: dacite (>=1.8.0,<2.0.0)
